ispir_currency_converter/__init__.py
ispir_currency_converter/converter.py
ispir_currency_converter-0.0.1.dist-info/METADATA
ispir_currency_converter-0.0.1.dist-info/WHEEL
ispir_currency_converter-0.0.1.dist-info/top_level.txt
ispir_currency_converter-0.0.1.dist-info/RECORD
